cannect/__init__.py
cannect/config.py
cannect/errors.py
cannect/api/__init__.py
cannect/core/__init__.py
cannect/core/mdf.py
cannect/core/subversion.py
cannect/core/ascet/__init__.py
cannect/core/ascet/amd.py
cannect/core/ascet/formula.py
cannect/core/ascet/oid.py
cannect/core/ascet/ws.py
cannect/core/can/__init__.py
cannect/core/can/rule.py
cannect/core/can/ascet/__init__.py
cannect/core/can/ascet/_db2code.py
cannect/core/can/ascet/_db2elem.py
cannect/core/can/ascet/comdef.py
cannect/core/can/ascet/comrx.py
cannect/core/can/ascet/diag.py
cannect/core/can/db/__init__.py
cannect/core/can/db/reader.py
cannect/core/can/db/schema.py
cannect/core/can/db/vcs.py
cannect/core/can/db/specification/__init__.py
cannect/core/can/db/specification/message.py
cannect/core/can/db/specification/styles.py
cannect/core/can/db/specification/wrapper.py
cannect/core/can/testcase/__init__.py
cannect/core/can/testcase/unitcase/__init__.py
cannect/core/can/testcase/unitcase/asw2can.py
cannect/core/can/testcase/unitcase/decode.py
cannect/core/can/testcase/unitcase/diagnosis.py
cannect/core/can/testcase/unitcase/encode.py
cannect/core/ir/__init__.py
cannect/core/ir/changehistory.py
cannect/core/ir/delivereables.py
cannect/core/ir/diff.py
cannect/core/ir/ir.py
cannect/core/ir/sdd.py
cannect/core/testcase/__init__.py
cannect/core/testcase/plotter.py
cannect/core/testcase/style.py
cannect/core/testcase/testcase.py
cannect/core/testcase/unitcase.py
cannect/schema/__init__.py
cannect/schema/candb.py
cannect/schema/datadictionary.py
cannect/utils/__init__.py
cannect/utils/excel.py
cannect/utils/logger.py
cannect/utils/ppt.py
cannect/utils/tools.py
cannect-1.0.2.dist-info/licenses/LICENSE
cannect-1.0.2.dist-info/METADATA
cannect-1.0.2.dist-info/WHEEL
cannect-1.0.2.dist-info/top_level.txt
cannect-1.0.2.dist-info/RECORD
