Metadata-Version: 2.4
Name: cannect
Version: 1.0.2
Summary: HYUNDAI-KEFICO EMS/ASW CONVENIENCE TOOL
Requires-Python: >=3.10
License-File: LICENSE
Requires-Dist: kaleido
Requires-Dist: lxml
Requires-Dist: mdfreader
Requires-Dist: numpy
Requires-Dist: pandas
Requires-Dist: plotly
Requires-Dist: psutil
Requires-Dist: pyautogui
Requires-Dist: pygetwindow
Requires-Dist: pyperclip
Requires-Dist: python-can
Requires-Dist: python-docx
Requires-Dist: python-dotenv
Requires-Dist: python-pptx
Requires-Dist: pywin32
Requires-Dist: tqdm
Requires-Dist: xlsxwriter
Dynamic: license-file
